undoom_pdf_mcp/__init__.py
undoom_pdf_mcp/__main__.py
undoom_pdf_mcp/main.py
undoom_pdf_mcp-0.2.3.dist-info/METADATA
undoom_pdf_mcp-0.2.3.dist-info/WHEEL
undoom_pdf_mcp-0.2.3.dist-info/entry_points.txt
undoom_pdf_mcp-0.2.3.dist-info/licenses/LICENSE
undoom_pdf_mcp-0.2.3.dist-info/RECORD
