Metadata-Version: 2.4
Name: undoom-pdf-mcp
Version: 0.2.3
Summary: PDF转换工具MCP服务器，集成PDF转图片、Office文件转PDF等功能
Project-URL: Homepage, https://github.com/kk520879/undoom_pdf_mcp
Project-URL: Repository, https://github.com/kk520879/undoom_pdf_mcp
Project-URL: Issues, https://github.com/kk520879/undoom_pdf_mcp/issues
Author-email: undoom <kaikaihuhu666@163.com>
License: MIT
License-File: LICENSE
Keywords: converter,image,mcp,office,pdf
Classifier: Development Status :: 4 - Beta
Classifier: Intended Audience :: Developers
Classifier: License :: OSI Approved :: MIT License
Classifier: Programming Language :: Python :: 3
Classifier: Programming Language :: Python :: 3.8
Classifier: Programming Language :: Python :: 3.9
Classifier: Programming Language :: Python :: 3.10
Classifier: Programming Language :: Python :: 3.11
Classifier: Programming Language :: Python :: 3.12
Classifier: Programming Language :: Python :: 3.13
Classifier: Topic :: Multimedia :: Graphics :: Graphics Conversion
Classifier: Topic :: Office/Business :: Office Suites
Classifier: Topic :: Software Development :: Libraries :: Python Modules
Requires-Python: >=3.10
Requires-Dist: mcp[cli]>=1.12.4
Requires-Dist: pillow>=10.0.0
Requires-Dist: pymupdf>=1.23.0
Requires-Dist: pywin32>=306; sys_platform == 'win32'
Requires-Dist: tkinterdnd2>=0.3.0
